Metadata-Version: 2.1
Name: wisedb
Version: 0.0.1
Summary: Wisedb
Author: MF
